LICENSE.md
MANIFEST.in
setup.py
jupyter_cms/__init__.py
jupyter_cms/_version.py
jupyter_cms/extensionapp.py
jupyter_cms/index.py
jupyter_cms/inject.py
jupyter_cms/loader.py
jupyter_cms/search.py
jupyter_cms/uploads.py
jupyter_cms.egg-info/PKG-INFO
jupyter_cms.egg-info/SOURCES.txt
jupyter_cms.egg-info/dependency_links.txt
jupyter_cms.egg-info/entry_points.txt
jupyter_cms.egg-info/requires.txt
jupyter_cms.egg-info/top_level.txt
jupyter_cms/nbextension/common/dnd_upload.css
jupyter_cms/nbextension/common/dnd_upload.js
jupyter_cms/nbextension/common/importer.js
jupyter_cms/nbextension/common/notify.css
jupyter_cms/nbextension/common/notify.js
jupyter_cms/nbextension/common/search.css
jupyter_cms/nbextension/common/search.js
jupyter_cms/nbextension/common/topics.js
jupyter_cms/nbextension/dashboard/main.js
jupyter_cms/nbextension/dashboard/search.js
jupyter_cms/nbextension/editor/main.js
jupyter_cms/nbextension/editor/search.js
jupyter_cms/nbextension/nls/messages.js
jupyter_cms/nbextension/notebook/main.js
jupyter_cms/nbextension/notebook/search.js
jupyter_cms/nbextension/notebook/toc.css
jupyter_cms/nbextension/notebook/toc.js
test/test_inject.py
test/test_loader.py