Metadata-Version: 1.1
Name: jupyter-cms
Version: 0.7.0
Summary: Extension for Jupyter Notebook 4.0.x with experimental content management features
Home-page: https://github.com/jupyter-incubator/contentmanagement
Author: Jupyter Development Team
Author-email: jupyter@googlegroups.com
License: BSD
Platform: Jupyter Notebook 4.0.x
Platform: Jupyter Notebook 4.1.x
Platform: Jupyter Notebook 4.2.x
Classifier: Intended Audience :: Developers
Classifier: Intended Audience :: System Administrators
Classifier: Intended Audience :: Science/Research
Classifier: License :: OSI Approved :: BSD License
Classifier: Programming Language :: Python
Classifier: Programming Language :: Python :: 2.7
Classifier: Programming Language :: Python :: 3.3
Classifier: Programming Language :: Python :: 3.4
Classifier: Programming Language :: Python :: 3.5
